openlane/mac_array_4x4/pe.v
module pe #(
    parameter DATA_WIDTH=8,
    parameter ACC_WIDTH=32
)(
    input wire clk,
    input wire rst_n,

    input wire signed [DATA_WIDTH-1:0] weight_in,
    input wire signed [DATA_WIDTH-1:0] act_in,
    input wire valid_in,
    input wire acc_clear,

    output reg signed [ACC_WIDTH-1:0] acc_out,
    output reg skipped,
    output reg mac_valid
);

wire is_weight_zero;
wire is_act_zero;
assign is_weight_zero=(weight_in==0);
assign is_act_zero=(act_in==0);
wire do_skip;
assign do_skip=valid_in && (is_weight_zero||is_act_zero);
wire do_mac;
assign do_mac=valid_in && !do_skip;
always @(posedge clk or negedge rst_n) begin
    if (!rst_n) begin
        acc_out<=0;
        skipped   <= 0;
        mac_valid <= 0;
    end
    else begin
        if (acc_clear) begin
            acc_out<=0;
        end
         else if (do_mac) begin
            acc_out<=acc_out + (weight_in * act_in);
        end
        skipped   <= do_skip;
        mac_valid <= do_mac;
    end
end


endmodule

tb/tb_pe.v
`timescale 1ns/1ps

module tb_pe;

    reg rst_n;
    reg valid_in;
    reg signed [7:0] weight_in;
    reg signed [7:0] act_in;
    reg acc_clear;

    wire signed [31:0] acc_out;
    wire skipped;
    wire mac_valid;

    reg clk;
    integer errors;

    // 100 MHz clock
    always #5 clk = ~clk;

    initial begin
        // Waveform generation
        $dumpfile("tb_pe.vcd");
        $dumpvars(0, tb_pe);

        // Initial values
        clk       = 0;
        rst_n     = 0;
        valid_in  = 0;
        weight_in = 0;
        act_in    = 0;
        acc_clear = 0;
        errors    = 0;

        // ------------------------------------------------
        // Reset sequence
        // ------------------------------------------------
        repeat (2) @(negedge clk);
        rst_n = 1;

        // ------------------------------------------------
        // Test 1: Normal MAC - 3 × 4
        // Expected ACC = 12
        // ------------------------------------------------
        @(negedge clk);
        weight_in = 3;
        act_in    = 4;
        valid_in  = 1;

        @(posedge clk);
        #1;

        if (acc_out == 12)
            $display("PASS: 3 x 4 MAC produced ACC = 12");
        else begin
            $display("FAIL: expected ACC = 12, got %0d", acc_out);
            errors = errors + 1;
        end

        // ------------------------------------------------
        // Test 2: Zero weight - 0 × 7
        // Expected: SKIP, ACC remains 12
        // ------------------------------------------------
        @(negedge clk);
        weight_in = 0;
        act_in    = 7;
        valid_in  = 1;

        @(posedge clk);
        #1;

        if (skipped && !mac_valid && acc_out == 12)
            $display("PASS: zero-weight MAC correctly skipped, ACC remains 12");
        else begin
            $display("FAIL: zero-weight skip did not behave correctly");
            errors = errors + 1;
        end

        // ------------------------------------------------
        // Test 3: Zero activation - 9 × 0
        // Expected: SKIP, ACC remains 12
        // ------------------------------------------------
        @(negedge clk);
        weight_in = 9;
        act_in    = 0;
        valid_in  = 1;

        @(posedge clk);
        #1;

        if (skipped && !mac_valid && acc_out == 12)
            $display("PASS: zero-activation MAC correctly skipped, ACC remains 12");
        else begin
            $display("FAIL: zero-activation skip did not behave correctly");
            errors = errors + 1;
        end

        // ------------------------------------------------
        // Test 4: Normal MAC after skips - 10 × 10
        // Expected: 12 + 100 = 112
        // ------------------------------------------------
        @(negedge clk);
        weight_in = 10;
        act_in    = 10;
        valid_in  = 1;

        @(posedge clk);
        #1;

        if (mac_valid && !skipped && acc_out == 112)
            $display("PASS: MAC resumed correctly after skips, ACC = 112");
        else begin
            $display("FAIL: MAC after skips incorrect, ACC = %0d", acc_out);
            errors = errors + 1;
        end

        // ------------------------------------------------
        // Test 5: Accumulator clear
        // Expected ACC = 0
        // ------------------------------------------------
        @(negedge clk);
        acc_clear = 1;
        valid_in  = 0;

        @(posedge clk);
        #1;

        if (acc_out == 0)
            $display("PASS: accumulator clear reset ACC to 0");
        else begin
            $display("FAIL: accumulator clear failed, ACC = %0d", acc_out);
            errors = errors + 1;
        end

        acc_clear = 0;

        // ------------------------------------------------
        // Test 6: MAC after accumulator clear - 6 × 6
        // Expected ACC = 36
        // ------------------------------------------------
        @(negedge clk);
        weight_in = 6;
        act_in    = 6;
        valid_in  = 1;

        @(posedge clk);
        #1;

        if (mac_valid && !skipped && acc_out == 36)
            $display("PASS: MAC worked correctly after clear, ACC = 36");
        else begin
            $display("FAIL: MAC after clear incorrect, ACC = %0d", acc_out);
            errors = errors + 1;
        end

        // ------------------------------------------------
        // Final test summary
        // ------------------------------------------------
        if (errors == 0)
            $display("ALL TESTS PASSED");
        else
            $display("%0d TEST(S) FAILED", errors);

        // End simulation
        $finish;
    end

    // Device Under Test
    pe dut (
        .clk       (clk),
        .rst_n     (rst_n),
        .valid_in  (valid_in),
        .weight_in (weight_in),
        .act_in    (act_in),
        .acc_clear (acc_clear),
        .acc_out   (acc_out),
        .skipped   (skipped),
        .mac_valid (mac_valid)
    );

endmodule

tb_pe.vcd
$date
	Sun Aug 23 07:11:33 2026
$end
$version
	Icarus Verilog
$end
$timescale
	1ps
$end
$scope module tb_pe $end
$var wire 1 ! skipped $end
$var wire 1 " mac_valid $end
$var wire 32 # acc_out [31:0] $end
$var reg 1 $ acc_clear $end
$var reg 8 % act_in [7:0] $end
$var reg 1 & clk $end
$var reg 1 ' rst_n $end
$var reg 1 ( valid_in $end
$var reg 8 ) weight_in [7:0] $end
$var integer 32 * errors [31:0] $end
$scope module dut $end
$var wire 1 $ acc_clear $end
$var wire 8 + act_in [7:0] $end
$var wire 1 & clk $end
$var wire 1 , do_mac $end
$var wire 1 - do_skip $end
$var wire 1 ' rst_n $end
$var wire 1 ( valid_in $end
$var wire 8 . weight_in [7:0] $end
$var wire 1 / is_weight_zero $end
$var wire 1 0 is_act_zero $end
$var parameter 32 1 ACC_WIDTH $end
$var parameter 32 2 DATA_WIDTH $end
$var reg 32 3 acc_out [31:0] $end
$var reg 1 " mac_valid $end
$var reg 1 ! skipped $end
$upscope $end
$upscope $end
$enddefinitions $end
$comment Show the parameter values. $end
$dumpall
b1000 2
b100000 1
$end
#0
$dumpvars
b0 3
10
1/
b0 .
0-
0,
b0 +
b0 *
b0 )
0(
0'
0&
b0 %
0$
b0 #
0"
0!
$end
#5000
1&
#10000
0&
#15000
1&
#20000
1'
0&
#25000
1&
#30000
1,
1(
00
b100 %
b100 +
0/
b11 )
b11 .
0&
#35000
1"
b1100 #
b1100 3
1&
#40000
0,
1-
b111 %
b111 +
1/
b0 )
b0 .
0&
#45000
0"
1!
1&
#50000
10
b0 %
b0 +
0/
b1001 )
b1001 .
0&
#55000
1&
#60000
1,
0-
00
b1010 %
b1010 +
b1010 )
b1010 .
0&
#65000
1"
0!
b1110000 #
b1110000 3
1&
#70000
0,
0(
1$
0&
#75000
0"
b0 #
b0 3
1&
#76000
0$
#80000
1,
1(
b110 %
b110 +
b110 )
b110 .
0&
#85000
1"
b100100 #
b100100 3
1&
